bingX/__init__.py
bingX/__version__.py
bingX/_helpers.py
bingX/_http_manager.py
bingX/exceptions.py
bingX/main.py
bingX/perpetual/__init__.py
bingX/perpetual/v1/__init__.py
bingX/perpetual/v1/perpetual.py
bingX/perpetual/v2/__init__.py
bingX/perpetual/v2/account.py
bingX/perpetual/v2/market.py
bingX/perpetual/v2/other.py
bingX/perpetual/v2/perpetual.py
bingX/perpetual/v2/trade.py
bingX/perpetual/v2/types.py
bingX/spot/__init__.py
bingX/spot/market.py
bingX/spot/other.py
bingX/spot/spot.py
bingX/spot/trade.py
bingX/spot/transfer.py
bingX/spot/types.py
bingX/standard/__init__.py
bingX/standard/standard.py
python_bingx-1.0.0.dist-info/LICENSE
python_bingx-1.0.0.dist-info/METADATA
python_bingx-1.0.0.dist-info/WHEEL
python_bingx-1.0.0.dist-info/top_level.txt
python_bingx-1.0.0.dist-info/RECORD
