Metadata-Version: 2.1
Name: python-bingx
Version: 1.0.0
Summary: Unofficial Python3 API connector for BingX's HTTP and WebSockets APIs.
Home-page: https://github.com/niewiemczego/python-bingx
Author: niewiemczego
License: MIT
Keywords: bingx exchange rest api bitcoin ethereum btc eth
Classifier: Intended Audience :: Developers
Classifier: License :: OSI Approved :: MIT License
Classifier: Operating System :: OS Independent
Classifier: Programming Language :: Python :: 3
Classifier: Programming Language :: Python :: 3.9
Classifier: Programming Language :: Python :: 3.10
Classifier: Programming Language :: Python :: 3.11
Classifier: Programming Language :: Python
Classifier: Topic :: Software Development :: Libraries :: Python Modules
License-File: LICENSE
Requires-Dist: requests
Requires-Dist: websockets
